wordpresspy/__init__.py
wordpresspy/api.py
wordpresspy/errors.py
wordpresspy/http_method.py
wordpresspy/utils.py
wordpresspy/woocommerce.py
wordpresspy/wordpress.py
wordpresspy-0.0.14.dist-info/METADATA
wordpresspy-0.0.14.dist-info/RECORD
wordpresspy-0.0.14.dist-info/WHEEL
wordpresspy-0.0.14.dist-info/top_level.txt
