Metadata-Version: 2.1
Name: wordpresspy
Version: 0.0.14
Summary: UNKNOWN
Home-page: https://github.com/weecan-group/wordpresspy
Author: Weecan
Author-email: contato@moacirbrg.org
License: MIT
Platform: UNKNOWN
Classifier: Programming Language :: Python :: 3
Classifier: License :: OSI Approved :: MIT License
Classifier: Operating System :: OS Independent
Requires-Dist: six
